vscrapper/__init__.py
vscrapper/search/__init__.py
vscrapper/types/__init__.py
vscrapper/utils/__init__.py
vscrapper/weburl/__init__.py
vscrapper-0.1.10.dist-info/METADATA
vscrapper-0.1.10.dist-info/WHEEL
vscrapper-0.1.10.dist-info/entry_points.txt
vscrapper-0.1.10.dist-info/RECORD
