Metadata-Version: 2.1
Name: vscrapper
Version: 0.1.10
Summary: 
Author: vikyw89
Author-email: vikyw89@gmail.com
Requires-Python: >=3.10,<4.0
Classifier: Programming Language :: Python :: 3
Classifier: Programming Language :: Python :: 3.10
Classifier: Programming Language :: Python :: 3.11
Classifier: Programming Language :: Python :: 3.12
Requires-Dist: validators (>=0.30.0,<0.31.0)
